{"2025-04-24": {"habit_0_1": false, "habit_0_2": true, "habit_0_3": true, "habit_0_4": true, "habit_0_5": false, "habit_0_6": true, "habit_0_7": false, "habit_1_1": false, "habit_1_2": false, "habit_1_3": false, "habit_1_4": false, "habit_1_5": false, "habit_1_6": false, "habit_1_7": false, "habit_2_1": false, "habit_2_2": true, "habit_2_3": false, "habit_2_4": false, "habit_2_5": false, "habit_2_6": true, "habit_2_7": true, "habit_3_1": false, "habit_3_2": true, "habit_3_3": false, "habit_3_4": false, "habit_3_5": true, "habit_3_6": true, "habit_3_7": true, "habit_4_1": false, "habit_4_2": false, "habit_4_3": false, "habit_4_4": true, "habit_4_5": false, "habit_4_6": true, "habit_4_7": true, "habit_5_1": false, "habit_5_2": false, "habit_5_3": true, "habit_5_4": true, "habit_5_5": false, "habit_5_6": false, "habit_5_7": true, "habit_6_1": true, "habit_6_2": true, "habit_6_3": true, "habit_6_4": true, "habit_6_5": false, "habit_6_6": true, "habit_6_7": true}}